devmail/__init__.py
devmail/_devmail.py
devmail/devmail.py
devmail-0.0.4.dist-info/LICENSE
devmail-0.0.4.dist-info/METADATA
devmail-0.0.4.dist-info/WHEEL
devmail-0.0.4.dist-info/top_level.txt
devmail-0.0.4.dist-info/RECORD
