Metadata-Version: 2.1
Name: devmail
Version: 0.0.4
Summary: DeveloperMail Python Wrapper
Home-page: https://github.com/faruqsandi/devmail
Author: Faruq Sandi
Author-email: <faruqsandi@email.com>
License: UNKNOWN
Project-URL: Bug Tracker, https://github.com/faruqsandi/devmail/issues
Keywords: python,developermail,temp mail,developer mail
Platform: UNKNOWN
Classifier: Development Status :: 3 - Alpha
Classifier: Intended Audience :: Developers
Classifier: Programming Language :: Python :: 3
Classifier: License :: OSI Approved :: MIT License
Classifier: Operating System :: OS Independent
Requires-Python: >=3.6
Requires-Dist: requests
